commentbegone/__init__.py
commentbegone/remove_comments.py
commentbegone/remove_comments_cli.py
commentbegone-2.0.2.dist-info/METADATA
commentbegone-2.0.2.dist-info/WHEEL
commentbegone-2.0.2.dist-info/entry_points.txt
commentbegone-2.0.2.dist-info/RECORD
