Metadata-Version: 2.1
Name: commentbegone
Version: 2.0.2
Summary: A Python package to remove comments from Python code.
Author: Nitya Ranjan
Author-email: nitya.ranjan@clearobject.com
Requires-Python: >=3.8,<4.0
Classifier: Programming Language :: Python :: 3
Classifier: Programming Language :: Python :: 3.8
Classifier: Programming Language :: Python :: 3.9
Classifier: Programming Language :: Python :: 3.10
Classifier: Programming Language :: Python :: 3.11
Classifier: Programming Language :: Python :: 3.12
Classifier: Programming Language :: Python :: 3.13
Requires-Dist: regex (>=2024.11.6,<2025.0.0)
